setup.py
hakuir/__init__.py
hakuir/env.py
hakuir/image_restoration.py
hakuir/image_super_resolution.py
hakuir.egg-info/PKG-INFO
hakuir.egg-info/SOURCES.txt
hakuir.egg-info/dependency_links.txt
hakuir.egg-info/entry_points.txt
hakuir.egg-info/requires.txt
hakuir.egg-info/top_level.txt
hakuir/cli/__init__.py
hakuir/cli/cli.py
hakuir/cli/commands.py
hakuir/models/__init__.py
hakuir/models/base.py
hakuir/models/kohakunet/__init__.py
hakuir/models/kohakunet/model.py
hakuir/models/nafnet/__init__.py
hakuir/models/nafnet/model.py
hakuir/models/rgt/__init__.py
hakuir/models/rgt/model.py
hakuir/models/scunet/__init__.py
hakuir/models/scunet/model.py
hakuir/trainer/__init__.py
hakuir/trainer/dataset/__init__.py
hakuir/trainer/loss/__init__.py
hakuir/trainer/loss/basic.py
hakuir/trainer/trainer/__init__.py
hakuir/trainer/trainer/wrapper.py
hakuir/utils/__init__.py
hakuir/utils/img_process.py
hakuir/utils/utils.py
hakuir/utils/xformers_utils.py