Metadata-Version: 2.1
Name: hakuir
Version: 0.0.5
Requires-Dist: torch
Requires-Dist: torchvision
Requires-Dist: pillow
Requires-Dist: numpy
Requires-Dist: einops
Requires-Dist: thop
Requires-Dist: timm
Requires-Dist: toml
